{
  "Author": "кайт машина (Puni.sh)",
  "Name": "Avarice",
  "InternalName": "Avarice",
  "Description": "Positional feedback with pixel perfect rear/flank tracking, range indicators, and more.",
  "Punchline": "Positional feedback with pixel perfect rear/flank tracking, range indicators, and more.",
  "ApplicableVersion": "any",
  "RepoUrl": "https://github.com/ShiftyKiwi/Avarice",
  "IconUrl": "https://raw.githubusercontent.com/ShiftyKiwi/Avarice/main/Assets/avarice_icon.png",
    "Tags": [
        "combat"
    ],
    "DalamudApiLevel": 14
}
